libbiomedit/__init__.py
libbiomedit/archive.py
libbiomedit/crypt.py
libbiomedit/metadata.py
libbiomedit/portal.py
libbiomedit/py.typed
libbiomedit/version.py
libbiomedit/lib/__init__.py
libbiomedit/lib/classify.py
libbiomedit/lib/deserialize.py
libbiomedit/lib/secret.py
libbiomedit-0.6.5.dist-info/LICENSE
libbiomedit-0.6.5.dist-info/METADATA
libbiomedit-0.6.5.dist-info/WHEEL
libbiomedit-0.6.5.dist-info/top_level.txt
libbiomedit-0.6.5.dist-info/RECORD
