Metadata-Version: 2.1
Name: libbiomedit
Version: 0.6.5
Summary: Shared library for arround biomedit data transfer
Home-page: https://gitlab.com/biomedit/libbiomedit
Author: Robin Engler, Jarosław Surkont, Riccardo Muri, Gerhard Bräunlich, Christian Ribeaud, François Martin
Author-email: Robin.Engler@sib.swiss, riccardo.murri@id.ethz.ch, jaroslaw.surkont@unibas.ch, gerhard.braeunlich@id.ethz.ch, christian.ribeaud@karakun.com, francois.martin@karakun.com
License: LGPL3
Classifier: Programming Language :: Python :: 3
Classifier: Programming Language :: Python :: 3.7
Classifier: Programming Language :: Python :: 3.8
Classifier: Programming Language :: Python :: 3.9
Classifier: Programming Language :: Python :: 3.10
Classifier: Programming Language :: Python :: 3.11
Classifier: Programming Language :: Python :: 3.12
Classifier: License :: OSI Approved :: GNU Lesser General Public License v3 (LGPLv3)
Classifier: Operating System :: OS Independent
Requires-Python: >=3.7
License-File: LICENSE
Requires-Dist: gpg-lite >=0.12.3
Provides-Extra: dev
Requires-Dist: mypy ==1.8.0 ; extra == 'dev'
Requires-Dist: pytest ==8.0.0 ; extra == 'dev'
Requires-Dist: ruff ==0.2.0 ; extra == 'dev'
Requires-Dist: bandit ==1.7.7 ; extra == 'dev'
Requires-Dist: types-pkg-resources ; extra == 'dev'
